ntap/LM.py
ntap/RNN.py
ntap/SVM.py
ntap/__init__.py
ntap/data.py
ntap/helpers.py
ntap/models.py
ntap-1.0.13.dist-info/LICENSE.txt
ntap-1.0.13.dist-info/METADATA
ntap-1.0.13.dist-info/WHEEL
ntap-1.0.13.dist-info/top_level.txt
ntap-1.0.13.dist-info/RECORD
