Metadata-Version: 2.1
Name: ntap
Version: 1.0.13
Summary: NTAP - CSSL
Home-page: https://github.com/USC-CSSL/NTAP
Author: Praveen Patil
Author-email: pspatil@usc.edu
License: UNKNOWN
Platform: UNKNOWN
Classifier: Programming Language :: Python :: 3
Classifier: Programming Language :: Python :: 3.4
Classifier: Programming Language :: Python :: 3.5
Classifier: Programming Language :: Python :: 3.6
Classifier: Programming Language :: Python :: 3.7
Classifier: License :: OSI Approved :: MIT License
Classifier: Operating System :: OS Independent
Requires-Dist: absl-py (==0.7.1)
Requires-Dist: astor (==0.8.0)
Requires-Dist: boto (==2.49.0)
Requires-Dist: boto3 (==1.9.199)
Requires-Dist: botocore (==1.12.199)
Requires-Dist: certifi (==2019.6.16)
Requires-Dist: chardet (==3.0.4)
Requires-Dist: docutils (==0.14)
Requires-Dist: gast (==0.2.2)
Requires-Dist: gensim (==3.8.0)
Requires-Dist: google-pasta (==0.1.7)
Requires-Dist: grpcio (==1.22.0)
Requires-Dist: h5py (==2.9.0)
Requires-Dist: idna (==2.8)
Requires-Dist: jmespath (==0.9.4)
Requires-Dist: joblib (==0.13.2)
Requires-Dist: Keras-Applications (==1.0.8)
Requires-Dist: Keras-Preprocessing (==1.1.0)
Requires-Dist: Markdown (==3.1.1)
Requires-Dist: nltk (==3.4.4)
Requires-Dist: numpy (==1.17.0)
Requires-Dist: pandas (==0.25.0)
Requires-Dist: protobuf (==3.9.0)
Requires-Dist: python-dateutil (==2.8.0)
Requires-Dist: pytz (==2019.2)
Requires-Dist: requests (==2.22.0)
Requires-Dist: s3transfer (==0.2.1)
Requires-Dist: scikit-learn (==0.21.3)
Requires-Dist: scipy (==1.3.0)
Requires-Dist: six (==1.12.0)
Requires-Dist: sklearn (==0.0)
Requires-Dist: smart-open (==1.8.4)
Requires-Dist: tensorboard (==1.14.0)
Requires-Dist: tensorflow (==1.14.0)
Requires-Dist: tensorflow-estimator (==1.14.0)
Requires-Dist: termcolor (==1.1.0)
Requires-Dist: urllib3 (==1.25.3)
Requires-Dist: Werkzeug (==0.15.5)
Requires-Dist: wrapt (==1.11.2)
